promoted_python_delivery_client/__init__.py
promoted_python_delivery_client/client/__init__.py
promoted_python_delivery_client/client/api_delivery.py
promoted_python_delivery_client/client/api_metrics.py
promoted_python_delivery_client/client/client.py
promoted_python_delivery_client/client/delivery_request.py
promoted_python_delivery_client/client/delivery_request_state.py
promoted_python_delivery_client/client/delivery_request_validator.py
promoted_python_delivery_client/client/delivery_response.py
promoted_python_delivery_client/client/sampler.py
promoted_python_delivery_client/client/sdk_delivery.py
promoted_python_delivery_client/client/serde.py
promoted_python_delivery_client/client/two_arm_experiment.py
promoted_python_delivery_client/client/version.py
promoted_python_delivery_client/model/__init__.py
promoted_python_delivery_client/model/blender_config.py
promoted_python_delivery_client/model/blender_rule.py
promoted_python_delivery_client/model/browser.py
promoted_python_delivery_client/model/client_hint_brand.py
promoted_python_delivery_client/model/client_hints.py
promoted_python_delivery_client/model/client_info.py
promoted_python_delivery_client/model/client_type.py
promoted_python_delivery_client/model/cohort_arm.py
promoted_python_delivery_client/model/cohort_membership.py
promoted_python_delivery_client/model/delivery_execution.py
promoted_python_delivery_client/model/delivery_log.py
promoted_python_delivery_client/model/device.py
promoted_python_delivery_client/model/execution_server.py
promoted_python_delivery_client/model/insertion.py
promoted_python_delivery_client/model/locale.py
promoted_python_delivery_client/model/location.py
promoted_python_delivery_client/model/log_request.py
promoted_python_delivery_client/model/paging.py
promoted_python_delivery_client/model/paging_info.py
promoted_python_delivery_client/model/properties.py
promoted_python_delivery_client/model/quality_score_config.py
promoted_python_delivery_client-2.2.0.dist-info/LICENSE
promoted_python_delivery_client-2.2.0.dist-info/METADATA
promoted_python_delivery_client-2.2.0.dist-info/WHEEL
promoted_python_delivery_client-2.2.0.dist-info/top_level.txt
promoted_python_delivery_client-2.2.0.dist-info/RECORD
