Metadata-Version: 2.1
Name: promoted-python-delivery-client
Version: 2.2.0
Summary: Promoted.ai Python Delivery Client
Home-page: https://github.com/promotedai/promoted-python-delivery-client
Author: Scott McMaster
Author-email: scott@promoted.ai
License: MIT
Classifier: Intended Audience :: Developers
Classifier: License :: OSI Approved :: MIT License
Classifier: Programming Language :: Python
Classifier: Programming Language :: Python :: 3
Classifier: Programming Language :: Python :: 3.6
Classifier: Programming Language :: Python :: 3.7
Classifier: Programming Language :: Python :: 3.8
Classifier: Programming Language :: Python :: 3.9
Classifier: Operating System :: OS Independent
License-File: LICENSE
Requires-Dist: dataclasses-json
Requires-Dist: requests
Requires-Dist: ujson
